README.md
setup.cfg
setup.py
cianparser/__init__.py
cianparser/cianparser.py
cianparser/constants.py
cianparser/definer_cities_id.py
cianparser/rentsparser.py
python_parser_cian.egg-info/PKG-INFO
python_parser_cian.egg-info/SOURCES.txt
python_parser_cian.egg-info/dependency_links.txt
python_parser_cian.egg-info/requires.txt
python_parser_cian.egg-info/top_level.txt