Metadata-Version: 2.1
Name: python-parser-cian
Version: 0.1
Summary: Parser information from Cian website
Home-page: https://github.com/lenarsaitov/cianparser
Author: Lenar Saitov
Author-email: lenarsaitov1@yandex.ru
License: MIT
Keywords: python parser requests beautifulsoup cian
Platform: UNKNOWN
